invpy/invpy.py
invpy/scrape.py
invpy/test.py
invpy-0.0.3.dist-info/METADATA
invpy-0.0.3.dist-info/RECORD
invpy-0.0.3.dist-info/WHEEL
invpy-0.0.3.dist-info/top_level.txt
